angets/__init__.py
angets/_core.py
angets/_decorators.py
angets/_defaults.py
angets/_exceptions.py
angets/_helpers.py
angets/py.typed
angets-0.2.2.dist-info/LICENSE
angets-0.2.2.dist-info/METADATA
angets-0.2.2.dist-info/WHEEL
angets-0.2.2.dist-info/top_level.txt
angets-0.2.2.dist-info/RECORD
