Metadata-Version: 2.2
Name: angets
Version: 0.2.2
Summary: Angets (Ankha's Gets): Functions for user input.
Author-email: Ankhbold Batbaatar <ankhasgreens@gmail.com>
Maintainer-email: Ankhbold Batbaatar <ankhasgreens@gmail.com>
License: MIT
Project-URL: Homepage, https://github.com/FirstlyBoldly/Angets
Project-URL: Issues, https://github.com/FirstlyBoldly/Angets/issues
Keywords: Ankha's Greens,user input,gets
Classifier: License :: OSI Approved :: MIT License
Classifier: Development Status :: 3 - Alpha
Classifier: Intended Audience :: Developers
Classifier: Topic :: Software Development :: Build Tools
Classifier: Programming Language :: Python :: 3
Classifier: Programming Language :: Python :: 3.11
Classifier: Programming Language :: Python :: 3.12
Classifier: Programming Language :: Python :: 3.13
Classifier: Operating System :: OS Independent
Classifier: Framework :: tox
Classifier: Typing :: Typed
Requires-Python: >=3.11
License-File: LICENSE
